nana_bot/__init__.py
nana_bot/bot.py
nana_bot/commands/__init__.py
nana_bot/commands/aibrowse_command.py
nana_bot/commands/analytics_command.py
nana_bot/commands/pass_command.py
nana_bot/commands/point_command.py
nana_bot/commands/search_command.py
nana_bot-5.8.9.9.8.8.7.7.6.9.dist-info/licenses/LICENSE
nana_bot-5.8.9.9.8.8.7.7.6.9.dist-info/METADATA
nana_bot-5.8.9.9.8.8.7.7.6.9.dist-info/WHEEL
nana_bot-5.8.9.9.8.8.7.7.6.9.dist-info/entry_points.txt
nana_bot-5.8.9.9.8.8.7.7.6.9.dist-info/top_level.txt
nana_bot-5.8.9.9.8.8.7.7.6.9.dist-info/RECORD
