Metadata-Version: 2.4
Name: nana-bot
Version: 5.8.9.9.8.8.7.7.6.9
Summary: A helpful Discord bot powered by Gemini
Home-page: https://github.com/vito1317/nana-bot
Author: Vito1317
Author-email: service@vito1317.com
License: MIT
Classifier: Programming Language :: Python :: 3
Classifier: License :: OSI Approved :: MIT License
Classifier: Operating System :: OS Independent
Requires-Python: >=3.9
License-File: LICENSE
Requires-Dist: pyparsing>=3.0.0
Requires-Dist: urllib3<2.0,>=1.26.0
Requires-Dist: discord.py
Requires-Dist: google-auth!=2.24.0,!=2.25.0,<3.0.0,>=2.14.1
Requires-Dist: rsa<5.0,>=4.8
Requires-Dist: pyasn1>=0.4.8
Requires-Dist: pyasn1-modules>=0.2.7
Requires-Dist: protobuf<5.0.0,>=3.20.2
Requires-Dist: google-generativeai
Requires-Dist: requests
Requires-Dist: beautifulsoup4
Requires-Dist: discord-interactions
Requires-Dist: requests
Requires-Dist: aiohttp
Requires-Dist: search-engine-tool-vito1317
Requires-Dist: python-dotenv
Requires-Dist: gtts
Requires-Dist: pyttsx3
Requires-Dist: google-cloud-speech
Requires-Dist: torchaudio
Requires-Dist: edge_tts
Requires-Dist: SpeechRecognition
Requires-Dist: py-cord
Requires-Dist: soundfile
Requires-Dist: discord-ext-voice-recv[extras]
Requires-Dist: whisper
Requires-Dist: google.genai
Requires-Dist: opencv-python
Requires-Dist: pillow
Requires-Dist: mss
Dynamic: author
Dynamic: author-email
Dynamic: classifier
Dynamic: description
Dynamic: description-content-type
Dynamic: home-page
Dynamic: license
Dynamic: license-file
Dynamic: requires-dist
Dynamic: requires-python
Dynamic: summary
